handshake.v
module handshake(

    input clk,
    input rst_n,
    input out_ready,

    output reg out_valid,
    output reg [7:0] out_data

);

always @(posedge clk) begin

    if(!rst_n) begin
        out_valid <= 0;
        out_data <= 0;
    end

    else begin

        out_valid <= 1;

        if(out_valid && out_ready)
            out_data <= out_data + 1;

    end

end

endmodule

handshake_tb.v
`timescale 1ns/1ps

module handshake_tb;

reg clk;
reg rst_n;
reg out_ready;

wire out_valid;
wire [7:0] out_data;

handshake DUT(

    .clk(clk),
    .rst_n(rst_n),
    .out_ready(out_ready),
    .out_valid(out_valid),
    .out_data(out_data)

);

initial begin

    clk = 0;

    forever #5 clk = ~clk;

end

initial begin

    $dumpfile("handshake.vcd");
    $dumpvars(0,handshake_tb);

    rst_n = 0;
    out_ready = 0;

    #20;

    rst_n = 1;

    #20;
    out_ready = 1;

    #40;
    out_ready = 0;

    #40;
    out_ready = 1;

    #60;

    $finish;

end

endmodule

handshake.vcd
$date
	Thu Aug  6 04:40:10 2026
$end
$version
	Icarus Verilog
$end
$timescale
	1ps
$end
$scope module handshake_tb $end
$var wire 1 ! out_valid $end
$var wire 8 " out_data [7:0] $end
$var reg 1 # clk $end
$var reg 1 $ out_ready $end
$var reg 1 % rst_n $end
$scope module DUT $end
$var wire 1 # clk $end
$var wire 1 $ out_ready $end
$var wire 1 % rst_n $end
$var reg 8 & out_data [7:0] $end
$var reg 1 ! out_valid $end
$upscope $end
$upscope $end
$enddefinitions $end
$comment Show the parameter values. $end
$dumpall
$end
#0
$dumpvars
bx &
0%
0$
0#
bx "
x!
$end
#5000
b0 "
b0 &
0!
1#
#10000
0#
#15000
1#
#20000
0#
1%
#25000
1!
1#
#30000
0#
#35000
1#
#40000
0#
1$
#45000
b1 "
b1 &
1#
#50000
0#
#55000
b10 "
b10 &
1#
#60000
0#
#65000
b11 "
b11 &
1#
#70000
0#
#75000
b100 "
b100 &
1#
#80000
0#
0$
#85000
1#
#90000
0#
#95000
1#
#100000
0#
#105000
1#
#110000
0#
#115000
1#
#120000
0#
1$
#125000
b101 "
b101 &
1#
#130000
0#
#135000
b110 "
b110 &
1#
#140000
0#
#145000
b111 "
b111 &
1#
#150000
0#
#155000
b1000 "
b1000 &
1#
#160000
0#
#165000
b1001 "
b1001 &
1#
#170000
0#
#175000
b1010 "
b1010 &
1#
